{
    "line": [
        {
            "id": "l_00",
            "label": "তেমনই বাংলাদেশও তার প্রয়জনীয় সকল উপাদান"
        },
        {
            "id": "l_01",
            "label": "নিজে উৎপাদন করতে পারে না। তাই প্রতিটি"
        },
        {
            "id": "l_02",
            "label": "দেশের জন্য আমদানি ও রপ্তানি উভই গুরুত্বপূর্ণ।"
        },
        {
            "id": "l_03",
            "label": "নিচে &garb বাংলাদেশের আমদানি ও রপ্তানি"
        },
        {
            "id": "l_04",
            "label": "পন্য সমগ্র সম্পর্কে আলোচনা করা হলোঃ"
        },
        {
            "id": "l_05",
            "label": "পৃথিবীবর বিভিন্ন দেশ থেকে চাল, ডাল, গম, তৈলবীজ,"
        },
        {
            "id": "l_06",
            "label": "তুলা, অপরিশোবিত পেট্রোল, পেট্রালিয়ামজাত দ্রব্য,"
        },
        {
            "id": "l_07",
            "label": "ভাজ্যতেল, সার, কৃষি ও শিল্প যন্ত্রপাতি ইত্যাদি প্রতি-"
        },
        {
            "id": "l_08",
            "label": "নিয়ত নানাভাবে বাংলাদেশে আমদানি করা হয়।"
        },
        {
            "id": "l_09",
            "label": "সরকারি ও বেসরকারী উভই খাতে এ বানিঝ্য চলে।"
        }
    ],
    "imagePath": "136_0.jpg",
    "imageHeight": 2329,
    "imageWidth": 2779
}